coinex/__init__.py
coinex-0.1.0.dist-info/DESCRIPTION.rst
coinex-0.1.0.dist-info/METADATA
coinex-0.1.0.dist-info/RECORD
coinex-0.1.0.dist-info/WHEEL
coinex-0.1.0.dist-info/metadata.json
coinex-0.1.0.dist-info/top_level.txt
